pwact/__init__.py
pwact/main.py
pwact/active_learning/__init__.py
pwact/active_learning/environment.py
pwact/active_learning/slurm.py
pwact/active_learning/explore/__init__.py
pwact/active_learning/explore/run_model_md.py
pwact/active_learning/explore/select_image.py
pwact/active_learning/init_bulk/__init__.py
pwact/active_learning/init_bulk/aimd.py
pwact/active_learning/init_bulk/duplicate_scale.py
pwact/active_learning/init_bulk/init_bulk_run.py
pwact/active_learning/init_bulk/relax.py
pwact/active_learning/label/__init__.py
pwact/active_learning/label/labeling.py
pwact/active_learning/test/__init__.py
pwact/active_learning/test/test.py
pwact/active_learning/train/__init__.py
pwact/active_learning/train/dp_kpu.py
pwact/active_learning/train/train_model.py
pwact/active_learning/user_input/__init__.py
pwact/active_learning/user_input/cmd_infos.py
pwact/active_learning/user_input/init_bulk_input.py
pwact/active_learning/user_input/iter_input.py
pwact/active_learning/user_input/resource.py
pwact/active_learning/user_input/scf_param.py
pwact/active_learning/user_input/workdir.py
pwact/active_learning/user_input/train_param/__init__.py
pwact/active_learning/user_input/train_param/model_param.py
pwact/active_learning/user_input/train_param/nep_param.py
pwact/active_learning/user_input/train_param/nn_feature_type.py
pwact/active_learning/user_input/train_param/optimizer_param.py
pwact/active_learning/user_input/train_param/train_param.py
pwact/active_learning/user_input/train_param/work_file_param.py
pwact/bin/__init__.py
pwact/data_format/__init__.py
pwact/data_format/configop.py
pwact/utils/__init__.py
pwact/utils/constant.py
pwact/utils/file_operation.py
pwact/utils/format_input_output.py
pwact/utils/json_operation.py
pwact/utils/pre_al_data_util.py
pwact/utils/slurm_script.py
pwact/utils/app_lib/__init__.py
pwact/utils/app_lib/common.py
pwact/utils/app_lib/cp2k.py
pwact/utils/app_lib/lammps.py
pwact/utils/app_lib/pwmat.py
pwact-2024.3.dist-info/LICENSE
pwact-2024.3.dist-info/METADATA
pwact-2024.3.dist-info/WHEEL
pwact-2024.3.dist-info/entry_points.txt
pwact-2024.3.dist-info/top_level.txt
pwact-2024.3.dist-info/RECORD
