Metadata-Version: 2.1
Name: pwact
Version: 2024.3
Summary: PWACT is an open-source automated active learning platform based on PWMLFF for efficient data sampling.
Home-page: https://github.com/LonxunQuantum/PWact
Author: LonxunQuantum
Author-email: lonxun@pwmat.com
Classifier: Programming Language :: Python :: 3
Classifier: License :: OSI Approved :: GNU General Public License v3 (GPLv3)
Classifier: Operating System :: OS Independent
Requires-Python: >=3.9
License-File: LICENSE
